{
    "T1": {"day": "Monday", "start": "08:00", "end": "11:00"},
    "T2": {"day": "Monday", "start": "11:00", "end": "14:00"},
    "T3": {"day": "Monday", "start": "14:00", "end": "17:00"},
    "T4": {"day": "Tuesday", "start": "08:00", "end": "11:00"},
    "T5": {"day": "Tuesday", "start": "11:00", "end": "14:00"},
    "T6": {"day": "Tuesday", "start": "14:00", "end": "17:00"},
    "T7": {"day": "Wednesday", "start": "08:00", "end": "11:00"},
    "T8": {"day": "Wednesday", "start": "11:00", "end": "14:00"},
    "T9": {"day": "Wednesday", "start": "14:00", "end": "17:00"},
    "T10": {"day": "Thursday", "start": "08:00", "end": "11:00"},
    "T11": {"day": "Thursday", "start": "11:00", "end": "14:00"},
    "T12": {"day": "Thursday", "start": "14:00", "end": "17:00"},
    "T13": {"day": "Friday", "start": "08:00", "end": "11:00"},
    "T14": {"day": "Friday", "start": "11:00", "end": "14:00"},
    "T15": {"day": "Friday", "start": "14:00", "end": "17:00"}
}